.max-uv-version
peeler/__init__.py
peeler/cli.py
peeler/schema.py
peeler/toml_utils.py
peeler/utils.py
peeler/uv_utils.py
peeler/command/manifest.py
peeler/command/version.py
peeler/command/wheels.py
peeler/data/blender_manifest_schema.json
peeler/data/peeler_pyproject_schema.json
peeler/data/peeler_schema.json
peeler/manifest/validate.py
peeler/manifest/write.py
peeler/pyproject/__init__.py
peeler/pyproject/manifest_adapter.py
peeler/pyproject/parser.py
peeler/pyproject/update.py
peeler/pyproject/validator.py
peeler/wheels/download.py
peeler/wheels/lock.py
peeler-0.9.1.dist-info/METADATA
peeler-0.9.1.dist-info/WHEEL
peeler-0.9.1.dist-info/entry_points.txt
peeler-0.9.1.dist-info/licenses/LICENSE
peeler-0.9.1.dist-info/RECORD
