Metadata-Version: 2.4
Name: peeler
Version: 0.9.1
Summary: A tool to use a pyproject.toml instead of a blender_manifest.toml to build Blender add-ons
Project-URL: Homepage, https://github.com/Maxioum/Peeler
Project-URL: Repository, https://github.com/Maxioum/Peeler.git
Project-URL: Changelog, https://github.com/Maxioum/Peeler/releases
Project-URL: Issues, https://github.com/Maxioum/Peeler/issues
Author-email: Maxime Letellier <maxime.eliot.letellier@gmail.com>
License:                     GNU GENERAL PUBLIC LICENSE
License-File: LICENSE
Keywords: add-on,blender
Classifier: Development Status :: 2 - Pre-Alpha
Classifier: Intended Audience :: Developers
Classifier: Operating System :: OS Independent
Classifier: Programming Language :: Python :: 3
Classifier: Programming Language :: Python :: 3.11
Classifier: Topic :: Multimedia :: Graphics :: 3D Modeling
Classifier: Topic :: Multimedia :: Graphics :: 3D Rendering
Requires-Python: >=3.11
Requires-Dist: dep-logic>=0.4.11
Requires-Dist: jsonschema>=4.23.0
Requires-Dist: packaging>=24.2
Requires-Dist: pyproject-metadata>=0.9.0
Requires-Dist: rich>=13.9.4
Requires-Dist: tomlkit>=0.13.2
Requires-Dist: typer>=0.15.1
Requires-Dist: validate-pyproject>=0.23
Requires-Dist: wheel-filename>=1.4.2
Provides-Extra: uv
Requires-Dist: uv<=0.9.16; extra == 'uv'
Requires-Dist: uv>=0.7; extra == 'uv'
